armature/__init__.py
armature/_config.py
armature-0.0.1.dist-info/METADATA
armature-0.0.1.dist-info/RECORD
armature-0.0.1.dist-info/WHEEL
armature-0.0.1.dist-info/top_level.txt
