Metadata-Version: 2.1
Name: armature
Version: 0.0.1
Summary: Config package
Home-page: UNKNOWN
Author: ['Data Lab ProRail']
Author-email: UNKNOWN
License: UNKNOWN
Platform: UNKNOWN
Requires-Dist: pyyaml
